perceptron/__init__.py
perceptron/perceptron.py
perceptron_pkg_mirfan57-0.0.4.dist-info/LICENSE
perceptron_pkg_mirfan57-0.0.4.dist-info/METADATA
perceptron_pkg_mirfan57-0.0.4.dist-info/WHEEL
perceptron_pkg_mirfan57-0.0.4.dist-info/top_level.txt
perceptron_pkg_mirfan57-0.0.4.dist-info/RECORD
