Metadata-Version: 2.1
Name: perceptron-pkg-mirfan57
Version: 0.0.4
Summary: A small example package for perceptron
Home-page: https://github.com/mirfan57/perceptron-pkg
Author: mirfan57
Author-email: mohdirfan57@gmail.com
Project-URL: Bug Tracker, https://github.com/mirfan57/perceptron-pkg/issues
Classifier: Programming Language :: Python :: 3
Classifier: License :: OSI Approved :: MIT License
Classifier: Operating System :: OS Independent
Requires-Python: >=3.7
License-File: LICENSE
Requires-Dist: numpy (==1.23.2)
Requires-Dist: pandas (==1.4.3)
Requires-Dist: joblib (==1.1.0)
